[
    {
        "name": "優花",
        "message": "「あ、美鈴、あれ見てみなよ」"
    },
    {
        "name": "美鈴",
        "message": "「あ……神谷先輩……」"
    },
    {
        "message": "中庭で他の男子と仲良く話している神谷を見つけ、優花が楽しそうに美鈴へと話しかける。"
    },
    {
        "message": "だが、いつもは神谷を見るだけで照れていた美鈴は、いつもと違う様子を見せた。"
    },
    {
        "name": "優花",
        "message": "「あれ？　元気ないじゃん。どうしたの？」"
    },
    {
        "name": "美鈴",
        "message": "「ううん、別に……」"
    },
    {
        "name": "優花",
        "message": "「あ、もしかして、あたし達が知らない間に告白したとか？　それで振られたとか……」"
    },
    {
        "name": "有紗",
        "message": "「ちょっと優花、それはデリカシーなさ過ぎじゃない？」"
    },
    {
        "name": "優花",
        "message": "「あ、ごめんごめん。……本当にそうなの？」"
    },
    {
        "name": "美鈴",
        "message": "「してないって。わたしにそんな勇気ないもん」"
    },
    {
        "name": "優花",
        "message": "「あはは……まぁ、それもそっか」"
    },
    {
        "name": "有紗",
        "message": "「優花……それもデリカシー足りてないから」"
    },
    {
        "message": "美鈴の表情は暗い。"
    },
    {
        "message": "有紗には、美鈴が何を思っているのか分かってしまった。"
    },
    {
        "name": "有紗",
        "message": "（神谷先輩には、自分はふさわしくないって思ってるんだ……。つまり、昨日のことは覚えてるってことね）"
    },
    {
        "message": "神谷先輩から目をそらし立ち去っていく美鈴の背中を見ながら、有紗は心の中に苦しく熱い思いが広がっているのを感じていた。"
    }
]