[
    {
        "name": "ドグマス",
        "message": "「アルテミナの正体はまだ掴めないのか？」"
    },
    {
        "name": "セラ",
        "message": "「だって仕方ないでしょ。全然尻尾を出さないし、ユーリはあの通り役に立たないんだもの」"
    },
    {
        "name": "ディモン",
        "message": "「直接ユーリに探らせるのは無理じゃないかなぁ？」"
    },
    {
        "name": "セラ",
        "message": "「む……分かってるわよ。でも、あのクラスにいるのはほぼ間違いないんでしょ？」"
    },
    {
        "name": "ドグマス",
        "message": "「クラリオンの調査が正しければ、な」"
    },
    {
        "name": "セラ",
        "message": "（一応、あいつが間違えてる可能性も見越して他の学生を探ってるけど、さっぱりなのよね……）"
    },
    {
        "name": "セラ",
        "message": "（ったく、生真面目なクセに使えないんだから……）"
    },
    {
        "name": "ドグマス",
        "message": "「次の手は考えてあるのか？」"
    },
    {
        "name": "セラ",
        "message": "「もちろん。あぶり出してやるわよ。ユーリのいる教室に、この前細工してきたわ」"
    },
    {
        "name": "ディモン",
        "message": "「へぇ……なんだか面白そうだね」"
    },
    {
        "name": "セラ",
        "message": "「アンタはちょっかい出さないでよ？　今回こそユーリに役に立ってもらうわ。アタシは結果を待ってるだけで正体が分かるはずよ」"
    },
    {
        "name": "ディモン",
        "message": "「それは頼もしいね。いい報告を期待してるよ」"
    },
    {
        "name": "セラ",
        "message": "（ふん、そんな上から目線で話が出来るのも今のうちよ。今回はとっておきなんだから）"
    },
    {
        "message": "セラは心の中で呟くと、唇の端を吊り上げてニヤリと笑った。"
    }
]