[
    {
        "message": "このまま徹底的にレイプしてやる！！"
    },
    {
        "message": "恐怖に脅える未夏の目の前で俺は得意げに笑いながら頬に口付けした。"
    },
    {
        "name": "貴城",
        "message": "「楽しい夜にしてやるよ。お前もたっぷりと楽しめよ！」"
    },
    {
        "name": "未夏",
        "message": "「うんぐぅぅぅぅぅぅぅぅ」"
    },
    {
        "message": "これから我が身に降りかかるであろう惨事に驚愕して顔面が蒼白となる。"
    },
    {
        "message": "と、未夏は身体を震わせて、恐怖の余り失神してしまった。"
    },
    {
        "name": "貴城",
        "message": "「生のダッチワイフか！　それも悪くない。徹底的にやってやる！」"
    },
    {
        "message": "意識の有無などもはや無関係。"
    },
    {
        "message": "とにかく犯して犯して犯しまくってやる。"
    },
    {
        "message": "肉棒を取り出して、未夏の秘裂にあてがう。"
    },
    {
        "message": "肉と肉が擦れる乾いた感触。"
    },
    {
        "message": "それでも構わずに腰に力をこめて一気に差し入れた。"
    },
    {
        "message": "メリメリと膣壁と肉棒が擦れて肉を押し広げていく。"
    },
    {
        "message": "根元まで差し込むと、未夏の膣の奥にある子宮に亀頭が突き当たった。"
    },
    {
        "message": "膣壁が激しく肉棒を擦りあげて締め付けた。"
    },
    {
        "message": "腰をゆっくりと引いてスライドさせては、もう一度突き入れる。"
    },
    {
        "message": "やがて膣壁が俺の肉棒の形に広がり、馴染みだす。"
    },
    {
        "message": "それに応じて俺のピストンは激しさを増していく。"
    },
    {
        "message": "尻を両手で抑えて無我夢中で突き上げる。"
    },
    {
        "message": "ぶるんぷるんと揺れる胸にしゃぶりつきながら、俺は獣のように犯しつづけた。"
    },
    {
        "message": "擦れる膣壁の感触が俺の射精欲を刺激し始める。"
    },
    {
        "message": "未夏の柔らかい尻の肉を指がめり込むほど握り締めて、俺は未夏の子宮の中に精液を流し込んだ。"
    },
    {
        "message": "流し込む精液の躍動に合わせて、未夏の肉体がビクビクと波打つ。"
    },
    {
        "message": "欲望を徹底的に注ぎ込んで、俺は余韻を楽しみながら挿入した状態で回復を待った。"
    },
    {
        "message": "やがて肉棒が硬さを取り戻すと、また腰を動かす。"
    },
    {
        "message": "放出した白濁液のおかげで今度はスムーズにピストン運動ができた。"
    },
    {
        "message": "両手で胸をこねるように揉みしだく。"
    },
    {
        "message": "乳首を転がして下から持ち上げるように力を加えると、意識のない未夏の肉体が反応して見るまに乳首が硬直した。"
    },
    {
        "message": "両胸を握り締めて何度も腰を打ち付けているとまた快感が高まっていく。"
    },
    {
        "message": "今度は肉棒を引き抜いて未夏の顔面を汚してやった。"
    },
    {
        "message": "未夏の体内と顔はこれで俺の汚液の洗礼を受けたのだ。"
    },
    {
        "message": "それでも俺はまだ満足することなく再度挿入した。"
    },
    {
        "message": "今度は全身を汚してやる。"
    },
    {
        "message": "未夏の肉体はダッチワイフというわけだ。"
    },
    {
        "message": "膣を利用して快感を高めると、俺は肉棒を引き抜いて胸元に放出する。"
    },
    {
        "message": "飛び散る白濁液に未夏の全身が染まった。"
    },
    {
        "message": "それは俺にとって最高の瞬間だった。"
    }
]