[
    {
        "message": "「それに、動きづらいのは麻痺ガスのせいだから、少し時間が経てば動けるはず」"
    },
    {
        "name": "Ｂアルテミナ",
        "message": "「はぁっ……そうね、援護射撃くらいは出来るだろうし」"
    },
    {
        "message": "そう言うと、ブラックアルテミナはマグナスの背から降りた。"
    },
    {
        "message": "「マグナス、アルテミナを乗せてあげて。これじゃ走れないだろうし」"
    },
    {
        "name": "マグナス",
        "message": "「そうだな。分かった」"
    },
    {
        "message": "「ありがとう。マグナス、お願いね」"
    },
    {
        "message": "「ああ。三人でディモンを倒すぞ！」"
    },
    {
        "message": "校舎に背を向け、ブラックアルテミナは商店街に向かって走り出した。"
    },
    {
        "name": "アルテミナ",
        "message": "「ううん、私も行くわ。あなたも、それにマグナスも万全じゃないもの。戦力は多い方がいいわ」"
    }
]